{"frames": [

{
	"filename": "Beach-00002.png",
	"frame": {"x":0,"y":0,"w":400,"h":400},
	"rotated": false,
	"trimmed": false,
	"spriteSourceSize": {"x":0,"y":0,"w":400,"h":400},
	"sourceSize": {"w":400,"h":400}
},
{
	"filename": "Beach-00003.png",
	"frame": {"x":400,"y":0,"w":400,"h":400},
	"rotated": false,
	"trimmed": false,
	"spriteSourceSize": {"x":0,"y":0,"w":400,"h":400},
	"sourceSize": {"w":400,"h":400}
},
{
	"filename": "Beach-00004.png",
	"frame": {"x":800,"y":0,"w":400,"h":400},
	"rotated": false,
	"trimmed": false,
	"spriteSourceSize": {"x":0,"y":0,"w":400,"h":400},
	"sourceSize": {"w":400,"h":400}
},
{
	"filename": "Beach-00005.png",
	"frame": {"x":1200,"y":0,"w":400,"h":400},
	"rotated": false,
	"trimmed": false,
	"spriteSourceSize": {"x":0,"y":0,"w":400,"h":400},
	"sourceSize": {"w":400,"h":400}
},
{
	"filename": "Beach-00006.png",
	"frame": {"x":1600,"y":0,"w":400,"h":400},
	"rotated": false,
	"trimmed": false,
	"spriteSourceSize": {"x":0,"y":0,"w":400,"h":400},
	"sourceSize": {"w":400,"h":400}
},
{
	"filename": "Beach-00012.png",
	"frame": {"x":0,"y":400,"w":400,"h":400},
	"rotated": false,
	"trimmed": false,
	"spriteSourceSize": {"x":0,"y":0,"w":400,"h":400},
	"sourceSize": {"w":400,"h":400}
},
{
	"filename": "Beach-00013.png",
	"frame": {"x":400,"y":400,"w":400,"h":400},
	"rotated": false,
	"trimmed": false,
	"spriteSourceSize": {"x":0,"y":0,"w":400,"h":400},
	"sourceSize": {"w":400,"h":400}
},
{
	"filename": "Beach-00015.png",
	"frame": {"x":800,"y":400,"w":400,"h":400},
	"rotated": false,
	"trimmed": false,
	"spriteSourceSize": {"x":0,"y":0,"w":400,"h":400},
	"sourceSize": {"w":400,"h":400}
},
{
	"filename": "Beach-00016.png",
	"frame": {"x":1200,"y":400,"w":400,"h":400},
	"rotated": false,
	"trimmed": false,
	"spriteSourceSize": {"x":0,"y":0,"w":400,"h":400},
	"sourceSize": {"w":400,"h":400}
},
{
	"filename": "Beach-00019.png",
	"frame": {"x":1600,"y":400,"w":400,"h":400},
	"rotated": false,
	"trimmed": false,
	"spriteSourceSize": {"x":0,"y":0,"w":400,"h":400},
	"sourceSize": {"w":400,"h":400}
}],
"meta": {
	"app": "https://www.codeandweb.com/texturepacker",
	"version": "1.0",
	"image": "Beach_Sketch.png",
	"format": "RGBA8888",
	"size": {"w":2000,"h":800},
	"scale": "1",
	"smartupdate": "$TexturePacker:SmartUpdate:714439bdc6929b12048b987e5641783f:e967c3383a4ac89f3e6604d556a4d114:c4d8a1c9c3c0824991cc5a1709b22aa9$"
}
}
